drive_backup/__init__.py
drive_backup/__main__.py
drive_backup/cli/__init__.py
drive_backup/core/__init__.py
drive_backup/core/config.py
drive_backup/core/console.py
drive_backup/core/credentials.py
drive_backup/core/dfsmap.py
drive_backup/core/drivebackup.py
drive_backup/core/notifications/__init__.py
drive_backup/core/notifications/mac/build/Drive Backup Notifications.app/Contents/CodeResources
drive_backup/core/notifications/mac/build/Drive Backup Notifications.app/Contents/Frameworks/libswift_Concurrency.dylib
drive_backup/core/notifications/mac/build/Drive Backup Notifications.app/Contents/Info.plist
drive_backup/core/notifications/mac/build/Drive Backup Notifications.app/Contents/MacOS/Drive Backup Notifications
drive_backup/core/notifications/mac/build/Drive Backup Notifications.app/Contents/PkgInfo
drive_backup/core/notifications/mac/build/Drive Backup Notifications.app/Contents/Resources/AppIcon.icns
drive_backup/core/notifications/mac/build/Drive Backup Notifications.app/Contents/Resources/Assets.car
drive_backup/core/notifications/mac/build/Drive Backup Notifications.app/Contents/_CodeSignature/CodeResources
drive_backup/core/notifications/windows/build/Drive Backup Notifications.exe
drive_backup/core/progress.py
drive_backup/resources/__init__.py
drive_backup/resources/authentication_success.html
drive_backup/resources/credentials.json
drive_backup/resources/drive-backup-icon.png
drive_backup-2.0.0.dist-info/LICENSE.md
drive_backup-2.0.0.dist-info/METADATA
drive_backup-2.0.0.dist-info/WHEEL
drive_backup-2.0.0.dist-info/entry_points.txt
drive_backup-2.0.0.dist-info/RECORD
