Metadata-Version: 2.1
Name: drive-backup
Version: 2.0.0
Summary: Backup your Google Drive files locally.
Home-page: https://www.georgeh2os.com/Drive-Backup/
License: MIT
Keywords: Google Drive,backup
Author: George Waters
Author-email: gwatersdev@gmail.com
Requires-Python: >=3.11,<3.13
Classifier: Development Status :: 5 - Production/Stable
Classifier: Environment :: Console
Classifier: Intended Audience :: End Users/Desktop
Classifier: License :: OSI Approved :: MIT License
Classifier: Operating System :: OS Independent
Classifier: Programming Language :: Python :: 3
Classifier: Programming Language :: Python :: 3.11
Classifier: Programming Language :: Python :: 3.12
Classifier: Topic :: System :: Archiving :: Backup
Classifier: Topic :: Utilities
Requires-Dist: cachetools (==5.5.0)
Requires-Dist: certifi (==2024.8.30)
Requires-Dist: cffi (==1.17.1) ; platform_python_implementation != "PyPy"
Requires-Dist: charset-normalizer (==3.3.2)
Requires-Dist: click (==8.1.7)
Requires-Dist: colorama (==0.4.6) ; platform_system == "Windows"
Requires-Dist: cryptography (==43.0.1)
Requires-Dist: drive-backup-credentials (==0.2.1)
Requires-Dist: google-api-core (==2.20.0)
Requires-Dist: google-api-python-client (==2.147.0)
Requires-Dist: google-auth (==2.35.0)
Requires-Dist: google-auth-httplib2 (==0.2.0)
Requires-Dist: google-auth-oauthlib (==1.2.1)
Requires-Dist: googleapis-common-protos (==1.65.0)
Requires-Dist: httplib2 (==0.22.0)
Requires-Dist: idna (==3.10)
Requires-Dist: markdown-it-py (==3.0.0)
Requires-Dist: mdurl (==0.1.2)
Requires-Dist: oauthlib (==3.2.2)
Requires-Dist: pathvalidate (==3.2.1)
Requires-Dist: proto-plus (==1.24.0)
Requires-Dist: protobuf (==5.28.2)
Requires-Dist: pyasn1 (==0.6.1)
Requires-Dist: pyasn1-modules (==0.4.1)
Requires-Dist: pycparser (==2.22) ; platform_python_implementation != "PyPy"
Requires-Dist: pygments (==2.18.0)
Requires-Dist: pyparsing (==3.1.4)
Requires-Dist: requests (==2.32.3)
Requires-Dist: requests-oauthlib (==2.0.0)
Requires-Dist: rich (==13.8.1)
Requires-Dist: rsa (==4.9)
Requires-Dist: uritemplate (==4.1.1)
Requires-Dist: urllib3 (==2.2.3)
Project-URL: Issues, https://github.com/dunkmann00/Drive-Backup/issues
Project-URL: Repository, https://github.com/dunkmann00/Drive-Backup
